LICENSE
MANIFEST.in
README.md
requirements.txt
setup.cfg
setup.py
rspy/__init__.py
rspy/__version__.py
rspy.egg-info/PKG-INFO
rspy.egg-info/SOURCES.txt
rspy.egg-info/dependency_links.txt
rspy.egg-info/not-zip-safe
rspy.egg-info/requires.txt
rspy.egg-info/top_level.txt
rspy/ancillary/__init__.py
rspy/ancillary/array_manupulation.py
rspy/ancillary/trigonometry.py
rspy/angles/__init__.py
rspy/angles/angles.py
rspy/auxiliary/__init__.py
rspy/auxiliary/exceptions.py
rspy/auxiliary/operator.py
rspy/auxiliary/types.py
rspy/bin/__init__.py
rspy/bin/bin_units/__init__.py
rspy/bin/bin_units/conversion.c
rspy/bin/bin_units/conversion.pyx
rspy/bin/bin_units/units_wrapper.c
rspy/bin/bin_units/units_wrapper.pyx
rspy/constants/__init__.py
rspy/constants/constants.py
rspy/intensity/__init__.py
rspy/intensity/intensity.py
rspy/intensity/utility.py
rspy/phase/__init__.py
rspy/phase/phase.py
rspy/sensor/__init__.py
rspy/sensor/auxiliary.py
rspy/sensor/sensor.py
rspy/specials/__init__.py
rspy/specials/stats/__init__.py
rspy/specials/stats/stats.py
rspy/test/__init__.py
rspy/test/test_ancillary/__init__.py
rspy/test/test_ancillary/test_array_operations.py
rspy/test/test_ancillary/test_trig.py
rspy/test/test_angles/__init__.py
rspy/test/test_angles/test_callable_methods.py
rspy/test/test_angles/test_init.py
rspy/test/test_angles/test_normlize.py
rspy/test/test_angles/test_properties.py
rspy/test/test_angles/test_setter.py
rspy/test/test_auxiliary/__init__.py
rspy/test/test_auxiliary/test_operator.py
rspy/test/test_auxiliary/test_types.py
rspy/test/test_global/__init__.py
rspy/test/test_global/test_version.py
rspy/test/test_intensity/__init__.py
rspy/test/test_intensity/test_errors.py
rspy/test/test_intensity/test_init.py
rspy/test/test_intensity/test_utils.py
rspy/test/test_phase/__init__.py
rspy/test/test_phase/test_init.py
rspy/test/test_phase/test_properties.py
rspy/test/test_sensor/__init__.py
rspy/test/test_sensor/test_angles_callable_methods.py
rspy/test/test_sensor/test_l8_aster.py
rspy/test/test_sensor/test_waves_init_prop.py
rspy/test/test_specials/__init__.py
rspy/test/test_specials/test_stats/__init__.py
