Metadata-Version: 1.2
Name: rspy
Version: 0.0.2
Summary: Fundamental Formulas for Radar and Angle Management
Home-page: https://github.com/ibaris/rspy
Author: Ismail Baris
Maintainer: Ismail Baris
License: UNKNOWN
Keywords: radar,remote-sensing,optics,integration,microwave,estimation,physics,radiative transfer
Platform: UNKNOWN
Classifier: Intended Audience :: Science/Research
Classifier: Topic :: Scientific/Engineering :: Atmospheric Science
Classifier: Development Status :: 5 - Production/Stable
Classifier: Intended Audience :: Developers
Classifier: Natural Language :: English
Classifier: License :: Other/Proprietary License
Classifier: Operating System :: OS Independent
Classifier: Programming Language :: Python
Classifier: Programming Language :: Python :: 2
Classifier: Programming Language :: Python :: 2.7
Classifier: Programming Language :: Python :: 3
Classifier: Programming Language :: Python :: 3.3
Classifier: Programming Language :: Python :: 3.4
